build/lib/pyTEMlib/__init__.py
build/lib/pyTEMlib/animation.py
build/lib/pyTEMlib/atom_tools.py
build/lib/pyTEMlib/config_dir.py
build/lib/pyTEMlib/crystal_tools.py
build/lib/pyTEMlib/file_reader.py
build/lib/pyTEMlib/file_tools.py
build/lib/pyTEMlib/graph_tools.py
build/lib/pyTEMlib/graph_viz.py
build/lib/pyTEMlib/microscope.py
build/lib/pyTEMlib/probe_tools.py
build/lib/pyTEMlib/sidpy_tools.py
build/lib/pyTEMlib/simulation_tools.py
build/lib/pyTEMlib/test.py
build/lib/pyTEMlib/utilities.py
build/lib/pyTEMlib/version.py
build/lib/pyTEMlib/xrpa_x_sections.py
build/lib/pyTEMlib/diffraction_tools/__init__.py
build/lib/pyTEMlib/diffraction_tools/basic.py
build/lib/pyTEMlib/diffraction_tools/diffraction_plot.py
build/lib/pyTEMlib/diffraction_tools/dynamic.py
build/lib/pyTEMlib/diffraction_tools/kinematic.py
build/lib/pyTEMlib/eds_tools/__init__.py
build/lib/pyTEMlib/eds_tools/eds_tools.py
build/lib/pyTEMlib/eds_tools/eds_xsections.py
build/lib/pyTEMlib/eels_tools/__init__.py
build/lib/pyTEMlib/eels_tools/core_loss_tools.py
build/lib/pyTEMlib/eels_tools/eels_database.py
build/lib/pyTEMlib/eels_tools/interactive_eels.py
build/lib/pyTEMlib/eels_tools/low_loss_tools.py
build/lib/pyTEMlib/eels_tools/peak_fit_tools.py
build/lib/pyTEMlib/eels_tools/zero_loss_tools.py
build/lib/pyTEMlib/image_tools/__init__.py
build/lib/pyTEMlib/image_tools/image_atoms.py
build/lib/pyTEMlib/image_tools/image_clean.py
build/lib/pyTEMlib/image_tools/image_distortion.py
build/lib/pyTEMlib/image_tools/image_fft.py
build/lib/pyTEMlib/image_tools/image_graph.py
build/lib/pyTEMlib/image_tools/image_main.py
build/lib/pyTEMlib/image_tools/image_registration.py
build/lib/pyTEMlib/image_tools/image_utilities.py
build/lib/pyTEMlib/image_tools/image_window.py
build/lib/pyTEMlib/image_tools/simulation.py
pyTEMlib/__init__.py
pyTEMlib/animation.py
pyTEMlib/atom_tools.py
pyTEMlib/config_dir.py
pyTEMlib/crystal_tools.py
pyTEMlib/file_reader.py
pyTEMlib/file_tools.py
pyTEMlib/graph_tools.py
pytemlib-0.2026.1.3.dist-info/licenses/LICENSE
pytemlib-0.2026.1.3.dist-info/METADATA
pytemlib-0.2026.1.3.dist-info/WHEEL
pytemlib-0.2026.1.3.dist-info/entry_points.txt
pytemlib-0.2026.1.3.dist-info/top_level.txt
pytemlib-0.2026.1.3.dist-info/RECORD
