Metadata-Version: 2.4
Name: pyTEMlib
Version: 0.2026.1.3
Summary: pyTEM: TEM Data Quantification library through a model-based approach
Author-email: Gerd Duscher <gduscher@utk.edu>
License-Expression: MIT
Project-URL: Homepage, https://pycroscopy.github.io/pyTEMlib/about.html
Project-URL: Repository, https://github.com/pycroscopy/pyTEMlib
Project-URL: Documentation, https://pycroscopy.github.io/pyTEMlib/
Keywords: imaging,spectra,transmission,electron,microscopy,scientific,scanning,eels,visualization,processing,storage,hdf5,diffraction
Platform: Linux
Platform: Mac OSX
Platform: Windows 11/10
Classifier: Development Status :: 2 - Pre-Alpha
Classifier: Environment :: Console
Classifier: Intended Audience :: Science/Research
Classifier: Natural Language :: English
Classifier: Operating System :: OS Independent
Classifier: Programming Language :: Cython
Classifier: Programming Language :: Python :: 3
Classifier: Programming Language :: Python :: 3.10
Classifier: Programming Language :: Python :: 3.11
Classifier: Programming Language :: Python :: 3.12
Classifier: Programming Language :: Python :: 3.13
Classifier: Programming Language :: Python :: 3.14
Classifier: Programming Language :: Python :: Implementation :: CPython
Classifier: Topic :: Scientific/Engineering :: Information Analysis
Requires-Python: >=3.9
License-File: LICENSE
Requires-Dist: scipy
Requires-Dist: numpy
Requires-Dist: pillow
Requires-Dist: ase
Requires-Dist: tqdm
Requires-Dist: plotly
Requires-Dist: pandas
Requires-Dist: requests
Requires-Dist: lxml
Requires-Dist: ipympl
Requires-Dist: spglib
Requires-Dist: simpleitk
Requires-Dist: scikit-image
Requires-Dist: scikit-learn
Requires-Dist: pyNSID>=0.0.7
Requires-Dist: sidpy>=0.12.7
Requires-Dist: SciFiReaders>=0.12.4
Requires-Dist: xraylib
Provides-Extra: test
Requires-Dist: pytest; extra == "test"
Requires-Dist: pytest-runner; extra == "test"
Dynamic: license-file
